{
  "version": "0.3.3",
  "flags": {},
  "shapes": [
    {
      "label": "cone-yellow",
      "text": "",
      "points": [
        [
          0.0,
          455.0
        ],
        [
          31.0,
          532.0
        ]
      ],
      "group_id": null,
      "shape_type": "rectangle",
      "flags": {}
    },
    {
      "label": "cone-yellow",
      "text": "",
      "points": [
        [
          224.0,
          416.0
        ],
        [
          254.0,
          460.0
        ]
      ],
      "group_id": null,
      "shape_type": "rectangle",
      "flags": {}
    },
    {
      "label": "cone-yellow",
      "text": "",
      "points": [
        [
          161.0,
          402.0
        ],
        [
          182.0,
          435.0
        ]
      ],
      "group_id": null,
      "shape_type": "rectangle",
      "flags": {}
    },
    {
      "label": "cone-yellow",
      "text": "",
      "points": [
        [
          13.0,
          396.0
        ],
        [
          34.0,
          425.0
        ]
      ],
      "group_id": null,
      "shape_type": "rectangle",
      "flags": {}
    },
    {
      "label": "cone-blue",
      "text": "",
      "points": [
        [
          847.0,
          468.0
        ],
        [
          890.0,
          538.0
        ]
      ],
      "group_id": null,
      "shape_type": "rectangle",
      "flags": {}
    },
    {
      "label": "cone-blue",
      "text": "",
      "points": [
        [
          740.0,
          428.0
        ],
        [
          766.0,
          472.0
        ]
      ],
      "group_id": null,
      "shape_type": "rectangle",
      "flags": {}
    },
    {
      "label": "cone-blue",
      "text": "",
      "points": [
        [
          661.0,
          414.0
        ],
        [
          678.0,
          451.0
        ]
      ],
      "group_id": null,
      "shape_type": "rectangle",
      "flags": {}
    },
    {
      "label": "cone-blue",
      "text": "",
      "points": [
        [
          535.0,
          405.0
        ],
        [
          549.0,
          434.0
        ]
      ],
      "group_id": null,
      "shape_type": "rectangle",
      "flags": {}
    },
    {
      "label": "cone-blue",
      "text": "",
      "points": [
        [
          419.0,
          396.0
        ],
        [
          431.0,
          425.0
        ]
      ],
      "group_id": null,
      "shape_type": "rectangle",
      "flags": {}
    },
    {
      "label": "cone-blue",
      "text": "",
      "points": [
        [
          288.0,
          391.0
        ],
        [
          301.0,
          418.0
        ]
      ],
      "group_id": null,
      "shape_type": "rectangle",
      "flags": {}
    },
    {
      "label": "cone-blue",
      "text": "",
      "points": [
        [
          0.0,
          381.0
        ],
        [
          12.0,
          410.0
        ]
      ],
      "group_id": null,
      "shape_type": "rectangle",
      "flags": {}
    }
  ],
  "imagePath": "image-1585055984251497.png",
  "imageData": null,
  "imageHeight": 720,
  "imageWidth": 1280,
  "text": ""
}